fstringlt36/__init__.py
fstringlt36/fstringlt36.py
fstringlt36/regexs.py
fstringlt36-0.0.3.dist-info/LICENSE
fstringlt36-0.0.3.dist-info/METADATA
fstringlt36-0.0.3.dist-info/WHEEL
fstringlt36-0.0.3.dist-info/top_level.txt
fstringlt36-0.0.3.dist-info/RECORD
