Metadata-Version: 2.1
Name: fstringlt36
Version: 0.0.3
Summary: Python f-strings for before Python3.6
Home-page: https://github.com/mendelsshop/fstringlt36/
Author: Mendelsshop
Author-email: mendelsshop@gmail.com
License: MIT
Project-URL: Bug Tracker, https://github.com/mendelsshop/fstringlt36/issues
Platform: UNKNOWN
Classifier: Programming Language :: Python
Classifier: License :: OSI Approved :: MIT License
Classifier: Operating System :: OS Independent
License-File: LICENSE
